{
  "datasets": [
    {
      "dataset": "ZINC-12k",
      "examples": [
        {
          "input": "{\"edge_index\":[[0,1,1,1,1,2,3,4,4,4,5,6,6,6,7,8],[1,0,2,3,4,1,1,1,5,6,4,4,7,8,6,6]],\"node_feat\":[0,0,0,9,4,9,0,1,7],\"edge_attr\":[1,1,1,1,1,1,1,1,1,1,1,1,2,1,2,1],\"num_nodes\":9}",
          "output": "-2.9461827278137207",
          "metadata_fold": "train",
          "metadata_task_type": "regression",
          "metadata_row_index": 75415,
          "metadata_num_nodes": 9,
          "metadata_num_edges": 16
        },
        {
          "input": "{\"edge_index\":[[0,1,1,2,2,3,3,3,4,5,5,5,6,6,7,7,8,8,8,9,9,10,10,11,11,12,12,13,13,13],[1,0,2,1,3,2,4,5,3,3,6,13,5,7,6,8,7,9,13,8,10,9,11,10,12,11,13,5,8,12]],\"node_feat\":[0,0,1,0,1,0,2,2,0,0,0,0,0,0],\"edge_attr\":[1,1,1,1,1,1,2,1,2,1,2,1,2,1,1,1,1,2,1,2,1,1,2,2,1,1,2,1,1,2],\"num_nodes\":14}",
          "output": "1.1046369075775146",
          "metadata_fold": "train",
          "metadata_task_type": "regression",
          "metadata_row_index": 98031,
          "metadata_num_nodes": 14,
          "metadata_num_edges": 30
        },
        {
          "input": "{\"edge_index\":[[0,1,1,1,2,3,3,3,3,4,5,6,6,7,7,7,8,8,9,9,10,10,11,11,11,12,12,13,13,13,14,15],[1,0,2,3,1,1,4,5,6,3,3,3,7,6,8,11,7,9,8,10,9,11,7,10,12,11,13,12,14,15,13,13]],\"node_feat\":[0,0,1,0,0,0,0,2,0,0,0,4,0,8,0,0],\"edge_attr\":[1,1,2,1,2,1,1,1,1,1,1,1,1,1,1,1,1,1,1,1,1,1,1,1,1,1,1,1,1,1,1,1],\"num_nodes\":16}",
          "output": "-2.8423011302948",
          "metadata_fold": "train",
          "metadata_task_type": "regression",
          "metadata_row_index": 96707,
          "metadata_num_nodes": 16,
          "metadata_num_edges": 32
        },
        {
          "input": "{\"edge_index\":[[0,1,1,2,2,3,3,3,4,4,4,5,6,7,7,7,8,8,9,10,10,10,11,11,12,12,13,13,13,14,15,15,16,16],[1,0,2,1,3,2,4,7,3,5,6,4,4,3,8,10,7,9,8,7,11,16,10,12,11,13,12,14,15,13,13,16,10,15]],\"node_feat\":[0,0,0,8,0,0,0,4,0,10,0,0,0,0,0,0,0],\"edge_attr\":[1,1,1,1,1,1,1,1,1,1,1,1,1,1,1,1,1,1,1,1,2,1,2,1,1,2,2,1,1,1,1,2,1,2],\"num_nodes\":17}",
          "output": "-2.7945241928100586",
          "metadata_fold": "train",
          "metadata_task_type": "regression",
          "metadata_row_index": 179431,
          "metadata_num_nodes": 17,
          "metadata_num_edges": 34
        },
        {
          "input": "{\"edge_index\":[[0,1,1,1,2,2,3,3,4,4,5,5,5,6,6,6,7,7,8,8,9,9,9,10,10,11,11,12,12,13,13,14,14,14,15,15,16,16],[1,0,2,16,1,3,2,4,3,5,4,6,16,5,7,15,6,8,7,9,8,10,14,9,11,10,12,11,13,12,14,9,13,15,6,14,1,5]],\"node_feat\":[2,0,0,0,0,0,0,0,2,0,0,0,0,0,0,2,0],\"edge_attr\":[1,1,2,1,2,1,1,2,2,1,1,1,2,1,2,1,2,1,1,2,2,1,1,1,2,2,1,1,2,2,1,1,1,2,1,2,1,2],\"num_nodes\":17}",
          "output": "1.9416658878326416",
          "metadata_fold": "train",
          "metadata_task_type": "regression",
          "metadata_row_index": 103010,
          "metadata_num_nodes": 17,
          "metadata_num_edges": 38
        },
        {
          "input": "{\"edge_index\":[[0,1,1,1,2,2,3,3,4,4,4,5,5,6,6,6,7,7,8,8,9,9,10,10,11,11,11,12,12,13,13,13,14,14,15,15,16,16,17,17],[1,0,2,13,1,3,2,4,3,5,12,4,6,5,7,11,6,8,7,9,8,10,9,11,6,10,12,4,11,1,14,17,13,15,14,16,15,17,13,16]],\"node_feat\":[1,0,2,0,0,2,0,0,0,0,0,0,5,0,2,2,0,2],\"edge_attr\":[2,2,1,1,1,1,1,1,1,2,1,2,1,1,2,1,2,1,1,2,2,1,1,2,1,2,1,1,1,1,2,1,2,1,1,1,1,2,1,2],\"num_nodes\":18}",
          "output": "-0.2892216145992279",
          "metadata_fold": "train",
          "metadata_task_type": "regression",
          "metadata_row_index": 148712,
          "metadata_num_nodes": 18,
          "metadata_num_edges": 40
        },
        {
          "input": "{\"edge_index\":[[0,1,1,1,2,2,2,3,4,5,5,5,6,6,7,7,8,8,8,9,9,9,10,11,11,11,12,13,13,14,14,14,15,15,16,16,17,17,18,18],[1,0,2,5,1,3,4,2,2,1,6,18,5,7,6,8,7,9,17,8,10,11,9,9,12,13,11,11,14,13,15,16,14,16,14,15,8,18,5,17]],\"node_feat\":[0,4,0,2,1,2,0,0,8,4,0,0,1,2,0,0,0,0,0],\"edge_attr\":[1,1,1,1,1,1,2,1,2,1,1,1,1,1,1,1,1,1,1,1,1,1,1,1,2,1,2,1,1,1,1,1,1,1,1,1,1,1,1,1],\"num_nodes\":19}",
          "output": "-4.7989277839660645",
          "metadata_fold": "train",
          "metadata_task_type": "regression",
          "metadata_row_index": 49914,
          "metadata_num_nodes": 19,
          "metadata_num_edges": 40
        },
        {
          "input": "{\"edge_index\":[[0,1,1,1,2,2,3,3,4,4,4,5,6,6,6,7,7,8,8,9,9,9,10,11,11,11,12,13,13,14,14,14,15,15,16,16,17,17,18,18],[1,0,2,14,1,3,2,4,3,5,6,4,4,7,13,6,8,7,9,8,10,11,9,9,12,13,11,6,11,1,15,18,14,16,15,17,16,18,14,17]],\"node_feat\":[0,4,0,2,0,1,2,0,0,4,0,4,1,0,0,0,5,0,0],\"edge_attr\":[1,1,1,1,1,1,1,1,1,2,1,2,1,1,1,1,1,1,1,1,1,1,1,1,1,1,1,1,1,1,2,1,2,1,1,1,1,2,1,2],\"num_nodes\":19}",
          "output": "-0.5038977265357971",
          "metadata_fold": "train",
          "metadata_task_type": "regression",
          "metadata_row_index": 201939,
          "metadata_num_nodes": 19,
          "metadata_num_edges": 40
        },
        {
          "input": "{\"edge_index\":[[0,1,1,1,2,2,3,3,4,4,4,5,5,5,6,7,7,8,8,8,9,9,9,10,11,11,12,12,13,13,14,14,14,15,16,16,16,17,18,18],[1,0,2,18,1,3,2,4,3,5,16,4,6,7,5,5,8,7,9,14,8,10,11,9,9,12,11,13,12,14,8,13,15,14,4,17,18,16,1,16]],\"node_feat\":[0,4,0,0,2,0,1,2,0,0,3,0,0,0,0,9,4,0,0],\"edge_attr\":[1,1,1,1,1,1,1,1,1,1,1,1,2,1,2,1,1,1,2,1,2,1,1,1,1,2,2,1,1,2,1,2,1,1,1,1,1,1,1,1],\"num_nodes\":19}",
          "output": "1.4574344158172607",
          "metadata_fold": "train",
          "metadata_task_type": "regression",
          "metadata_row_index": 168185,
          "metadata_num_nodes": 19,
          "metadata_num_edges": 40
        },
        {
          "input": "{\"edge_index\":[[0,1,1,1,2,2,2,3,4,4,5,5,5,6,6,7,7,7,8,8,9,9,10,10,11,11,11,12,12,12,13,13,13,14,15,15,15,16,17,17,18,18,19,19],[1,0,2,19,1,3,4,2,2,5,4,6,19,5,7,6,8,11,7,9,8,10,9,11,7,10,12,11,13,18,12,14,15,13,13,16,17,15,15,18,12,17,1,5]],\"node_feat\":[0,0,0,9,5,0,0,8,0,0,0,4,0,0,0,2,0,2,0,0],\"edge_attr\":[1,1,2,1,2,1,1,1,1,1,1,1,2,1,1,1,1,1,1,1,1,1,1,1,1,1,1,1,2,1,2,1,1,1,1,1,1,1,1,2,1,2,1,2],\"num_nodes\":20}",
          "output": "-1.7869455814361572",
          "metadata_fold": "train",
          "metadata_task_type": "regression",
          "metadata_row_index": 26892,
          "metadata_num_nodes": 20,
          "metadata_num_edges": 44
        },
        {
          "input": "{\"edge_index\":[[0,1,1,2,2,3,3,4,4,4,5,5,6,6,7,7,8,8,8,9,9,9,10,10,11,11,11,12,13,13,13,14,14,15,15,16,16,17,17,18,18,18,19,19],[1,0,2,1,3,2,4,3,5,19,4,6,5,7,6,8,7,9,19,8,10,18,9,11,10,12,13,11,11,14,18,13,15,14,16,15,17,16,18,9,13,17,4,8]],\"node_feat\":[0,0,0,1,0,0,0,0,0,4,2,0,1,4,0,0,0,0,2,0],\"edge_attr\":[1,1,1,1,1,1,1,1,2,1,2,1,1,2,2,1,1,1,2,1,1,1,1,1,1,2,1,2,1,1,1,1,1,1,1,1,1,1,1,1,1,1,1,2],\"num_nodes\":20}",
          "output": "0.16847899556159973",
          "metadata_fold": "train",
          "metadata_task_type": "regression",
          "metadata_row_index": 144887,
          "metadata_num_nodes": 20,
          "metadata_num_edges": 44
        },
        {
          "input": "{\"edge_index\":[[0,1,1,1,2,2,3,3,4,4,5,5,6,6,6,7,7,8,8,8,9,10,10,10,11,11,12,12,13,13,14,14,14,15,15,16,16,16,17,18,19,19],[1,0,2,6,1,3,2,4,3,5,4,6,1,5,7,6,8,7,9,10,8,8,11,19,10,12,11,13,12,14,13,15,19,14,16,15,17,18,16,16,10,14]],\"node_feat\":[0,0,0,0,0,2,0,0,4,9,0,0,0,0,0,1,0,3,3,0],\"edge_attr\":[1,1,2,1,2,1,1,2,2,1,1,2,1,2,1,1,1,1,1,1,1,1,2,1,2,1,1,2,2,1,1,1,2,1,1,1,1,1,1,1,1,2],\"num_nodes\":20}",
          "output": "2.025374412536621",
          "metadata_fold": "train",
          "metadata_task_type": "regression",
          "metadata_row_index": 44323,
          "metadata_num_nodes": 20,
          "metadata_num_edges": 42
        },
        {
          "input": "{\"edge_index\":[[0,1,1,2,2,2,3,4,4,4,4,5,6,6,7,7,8,8,8,9,9,9,10,10,11,11,12,12,13,13,13,14,14,15,15,16,16,16,17,18,18,19,19,19,20,20],[1,0,2,1,3,4,2,2,5,6,20,4,4,7,6,8,7,9,20,8,10,19,9,11,10,12,11,13,12,14,19,13,15,14,16,15,17,18,16,16,19,9,13,18,4,8]],\"node_feat\":[0,1,0,1,0,3,0,0,2,0,0,0,8,0,0,0,0,6,0,0,0],\"edge_attr\":[1,1,1,1,2,1,2,1,1,1,1,1,1,1,1,1,1,1,1,1,2,1,2,1,1,2,2,1,1,2,1,2,1,1,2,2,1,1,1,1,2,1,1,2,1,1],\"num_nodes\":21}",
          "output": "-1.2990933656692505",
          "metadata_fold": "train",
          "metadata_task_type": "regression",
          "metadata_row_index": 68358,
          "metadata_num_nodes": 21,
          "metadata_num_edges": 46
        },
        {
          "input": "{\"edge_index\":[[0,1,1,1,2,3,3,4,4,5,5,6,6,6,7,7,7,8,9,9,9,10,10,11,11,11,12,12,13,13,14,14,14,15,16,16,17,17,18,18,19,19,19,20],[1,0,2,3,1,1,4,3,5,4,6,5,7,19,6,8,9,7,7,10,18,9,11,10,12,17,11,13,12,14,13,15,16,14,14,17,11,16,9,19,6,18,20,19]],\"node_feat\":[1,0,7,0,0,0,2,0,1,0,0,0,0,0,0,9,0,0,5,0,5],\"edge_attr\":[2,2,1,1,1,1,1,1,1,1,1,1,1,1,1,2,1,2,1,2,1,2,1,1,2,1,2,1,1,2,2,1,1,1,1,2,1,2,1,1,1,1,2,2],\"num_nodes\":21}",
          "output": "0.4446130096912384",
          "metadata_fold": "train",
          "metadata_task_type": "regression",
          "metadata_row_index": 185851,
          "metadata_num_nodes": 21,
          "metadata_num_edges": 44
        },
        {
          "input": "{\"edge_index\":[[0,1,1,1,2,2,2,3,4,4,5,5,6,6,7,7,7,8,8,9,9,9,10,11,11,12,12,13,13,13,14,14,15,15,15,16,16,16,17,18,19,19,20,20],[1,0,2,7,1,3,4,2,2,5,4,6,5,7,1,6,8,7,9,8,10,11,9,9,12,11,13,12,14,20,13,15,14,16,19,15,17,18,16,16,15,20,13,19]],\"node_feat\":[0,0,0,3,0,0,0,0,2,0,1,0,0,0,2,0,0,0,0,2,1],\"edge_attr\":[1,1,2,1,2,1,1,1,1,2,2,1,1,2,1,2,1,1,1,1,2,1,2,1,1,1,1,1,2,1,2,1,1,1,2,1,1,1,1,1,2,1,1,1],\"num_nodes\":21}",
          "output": "1.7689189910888672",
          "metadata_fold": "train",
          "metadata_task_type": "regression",
          "metadata_row_index": 197249,
          "metadata_num_nodes": 21,
          "metadata_num_edges": 44
        },
        {
          "input": "{\"edge_index\":[[0,1,1,2,2,2,3,3,4,4,5,5,5,6,6,6,6,7,8,8,9,9,9,10,11,11,11,12,12,13,13,14,14,14,15,16,16,17,17,17,18,19,20,20,21,21],[1,0,2,1,3,21,2,4,3,5,4,6,20,5,7,8,17,6,6,9,8,10,11,9,9,12,16,11,13,12,14,13,15,16,14,11,14,6,18,19,17,17,5,21,2,20]],\"node_feat\":[0,1,0,0,0,0,0,0,2,0,1,0,0,5,0,0,2,0,1,7,0,0],\"edge_attr\":[1,1,1,1,2,1,2,1,1,2,2,1,1,1,1,1,1,1,1,1,1,2,1,2,1,2,1,2,1,1,1,1,1,2,1,1,2,1,2,1,2,1,1,2,1,2],\"num_nodes\":22}",
          "output": "-0.9930555820465088",
          "metadata_fold": "train",
          "metadata_task_type": "regression",
          "metadata_row_index": 75442,
          "metadata_num_nodes": 22,
          "metadata_num_edges": 46
        },
        {
          "input": "{\"edge_index\":[[0,1,1,1,2,3,3,4,4,4,5,5,6,6,7,7,8,8,8,9,9,9,10,11,11,11,12,12,13,14,14,14,15,15,16,16,17,17,17,18,19,19,20,20,21,21],[1,0,2,3,1,1,4,3,5,21,4,6,5,7,6,8,7,9,21,8,10,11,9,9,12,14,11,13,12,11,15,20,14,16,15,17,16,18,19,17,17,20,14,19,4,8]],\"node_feat\":[0,0,1,2,0,0,0,0,0,0,1,4,0,2,0,0,0,0,3,0,2,0],\"edge_attr\":[1,1,2,1,2,1,1,1,2,1,2,1,1,2,2,1,1,1,2,1,2,1,2,1,1,1,1,3,3,1,2,1,2,1,1,2,2,1,1,1,1,2,1,2,1,2],\"num_nodes\":22}",
          "output": "0.6620503664016724",
          "metadata_fold": "train",
          "metadata_task_type": "regression",
          "metadata_row_index": 107928,
          "metadata_num_nodes": 22,
          "metadata_num_edges": 46
        },
        {
          "input": "{\"edge_index\":[[0,1,1,1,2,2,3,3,3,4,4,5,5,6,6,6,7,8,8,9,9,9,10,10,11,11,12,12,12,13,14,15,15,15,16,16,17,17,18,18,19,19,20,20,20,21],[1,0,2,15,1,3,2,4,9,3,5,4,6,5,7,8,6,6,9,3,8,10,9,11,10,12,11,13,14,12,12,1,16,20,15,17,16,18,17,19,18,20,15,19,21,20]],\"node_feat\":[1,0,2,0,0,0,0,3,0,0,1,0,0,3,3,0,0,0,2,0,0,6],\"edge_attr\":[2,2,1,1,1,1,1,2,1,2,1,1,2,2,1,1,1,1,2,1,2,1,1,1,1,1,1,1,1,1,1,1,2,1,2,1,1,2,2,1,1,2,1,2,1,1],\"num_nodes\":22}",
          "output": "2.054368257522583",
          "metadata_fold": "train",
          "metadata_task_type": "regression",
          "metadata_row_index": 136237,
          "metadata_num_nodes": 22,
          "metadata_num_edges": 46
        },
        {
          "input": "{\"edge_index\":[[0,1,1,1,2,2,3,3,4,4,5,5,5,6,6,7,7,7,8,8,9,9,9,10,11,11,11,12,12,13,13,14,15,15,15,16,16,17,17,18,18,18,19,20,21,21,22,22],[1,0,2,22,1,3,2,4,3,5,4,6,22,5,7,6,8,21,7,9,8,10,11,9,9,12,15,11,13,12,14,13,11,16,21,15,17,16,18,17,19,20,18,18,7,15,1,5]],\"node_feat\":[0,0,0,0,0,0,2,0,2,0,0,0,0,0,1,0,1,0,0,1,7,2,0],\"edge_attr\":[1,1,2,1,2,1,1,2,2,1,1,1,2,1,1,1,2,1,2,1,1,1,2,1,2,1,1,1,1,1,1,1,1,1,2,1,1,1,1,1,2,1,2,1,1,2,1,2],\"num_nodes\":23}",
          "output": "-0.8890123963356018",
          "metadata_fold": "train",
          "metadata_task_type": "regression",
          "metadata_row_index": 23960,
          "metadata_num_nodes": 23,
          "metadata_num_edges": 48
        },
        {
          "input": "{\"edge_index\":[[0,1,1,2,2,3,3,4,4,5,5,5,6,6,6,7,8,8,8,9,9,10,10,10,11,11,12,12,13,13,13,14,15,15,16,16,17,17,17,18,18,18,19,19,20,20,21,21,22,22],[1,0,2,1,3,2,4,3,5,4,6,17,5,7,8,6,6,9,17,8,10,9,11,16,10,12,11,13,12,14,15,13,13,16,10,15,5,8,18,17,19,22,18,20,19,21,20,22,18,21]],\"node_feat\":[0,0,1,0,0,2,0,1,4,1,0,0,0,0,3,0,0,4,0,0,5,0,0],\"edge_attr\":[1,1,1,1,1,1,1,1,1,1,1,1,1,2,1,2,1,1,1,1,1,1,2,1,2,1,1,2,2,1,1,1,1,2,1,2,1,1,1,1,2,1,2,1,1,1,1,2,1,2],\"num_nodes\":23}",
          "output": "0.5477955937385559",
          "metadata_fold": "train",
          "metadata_task_type": "regression",
          "metadata_row_index": 58520,
          "metadata_num_nodes": 23,
          "metadata_num_edges": 50
        },
        {
          "input": "{\"edge_index\":[[0,1,1,2,2,2,3,3,4,4,5,5,5,6,7,7,8,8,8,9,9,10,10,10,11,12,12,13,13,14,14,14,15,16,16,17,17,17,18,18,19,19,20,20,21,21,22,22],[1,0,2,1,3,8,2,4,3,5,4,6,7,5,5,8,2,7,9,8,10,9,11,12,10,10,13,12,14,13,15,16,14,14,17,16,18,22,17,19,18,20,19,21,20,22,17,21]],\"node_feat\":[0,1,0,0,0,0,6,0,0,2,0,1,2,0,4,1,0,0,0,0,0,0,0],\"edge_attr\":[1,1,1,1,2,1,2,1,1,2,2,1,1,1,1,2,1,2,1,1,1,1,2,1,2,1,1,1,1,1,1,1,1,1,1,1,2,1,2,1,1,2,2,1,1,2,1,2],\"num_nodes\":23}",
          "output": "1.5419625043869019",
          "metadata_fold": "train",
          "metadata_task_type": "regression",
          "metadata_row_index": 159926,
          "metadata_num_nodes": 23,
          "metadata_num_edges": 48
        },
        {
          "input": "{\"edge_index\":[[0,1,1,1,2,2,3,3,3,4,4,5,5,5,6,7,7,7,8,9,9,9,10,10,11,11,12,12,13,13,14,14,15,15,16,16,16,17,17,17,18,18,19,19,20,20,20,21,22,22,23,23],[1,0,2,16,1,3,2,4,14,3,5,4,6,7,5,5,8,9,7,7,10,13,9,11,10,12,11,13,9,12,3,15,14,16,1,15,17,16,18,23,17,19,18,20,19,21,22,20,20,23,17,22]],\"node_feat\":[0,0,0,0,2,0,1,4,0,2,0,2,0,2,0,0,0,2,0,0,8,0,0,0],\"edge_attr\":[1,1,2,1,2,1,1,1,2,1,1,1,2,1,2,1,1,1,1,1,1,1,1,2,2,1,1,2,1,2,2,1,1,2,1,2,1,1,1,1,1,1,1,1,1,1,1,1,1,1,1,1],\"num_nodes\":24}",
          "output": "-2.313990831375122",
          "metadata_fold": "train",
          "metadata_task_type": "regression",
          "metadata_row_index": 100702,
          "metadata_num_nodes": 24,
          "metadata_num_edges": 52
        },
        {
          "input": "{\"edge_index\":[[0,1,1,1,2,2,3,3,3,4,4,5,5,5,6,6,7,7,7,8,9,9,10,10,11,11,11,12,12,13,13,14,14,15,15,15,16,16,16,17,18,19,19,20,20,21,21,21,22,22,22,23],[1,0,2,22,1,3,2,4,21,3,5,4,6,19,5,7,6,8,9,7,7,10,9,11,10,12,15,11,13,12,14,13,15,11,14,16,15,17,18,16,16,5,20,19,21,3,20,22,1,21,23,22]],\"node_feat\":[0,0,2,0,0,0,2,0,1,0,0,2,0,0,8,0,0,0,0,0,0,0,2,0],\"edge_attr\":[1,1,2,1,2,1,1,2,1,2,1,1,1,2,1,1,1,2,1,2,1,1,1,1,1,1,1,1,2,2,1,1,2,1,2,1,1,1,1,1,1,2,1,1,2,1,2,1,1,1,1,1],\"num_nodes\":24}",
          "output": "0.053520917892456055",
          "metadata_fold": "train",
          "metadata_task_type": "regression",
          "metadata_row_index": 188506,
          "metadata_num_nodes": 24,
          "metadata_num_edges": 52
        },
        {
          "input": "{\"edge_index\":[[0,1,1,1,2,2,3,3,4,4,5,5,5,6,7,7,7,8,8,8,9,10,10,10,11,11,12,12,13,13,13,14,14,15,15,16,16,16,17,18,18,19,19,19,19,20,21,22,23,23],[1,0,2,7,1,3,2,4,3,5,4,6,7,5,1,5,8,7,9,10,8,8,11,23,10,12,11,13,12,14,23,13,15,14,16,15,17,18,16,16,19,18,20,21,22,19,19,19,10,13]],\"node_feat\":[0,4,0,0,0,4,0,2,0,1,0,0,0,0,0,2,0,1,1,0,0,0,0,1],\"edge_attr\":[1,1,1,1,1,1,1,1,1,1,1,1,1,1,1,1,1,1,2,1,2,1,2,1,2,1,1,2,2,1,1,1,1,1,1,1,2,1,2,1,1,1,1,1,1,1,1,1,1,1],\"num_nodes\":24}",
          "output": "0.9820955991744995",
          "metadata_fold": "train",
          "metadata_task_type": "regression",
          "metadata_row_index": 42930,
          "metadata_num_nodes": 24,
          "metadata_num_edges": 50
        },
        {
          "input": "{\"edge_index\":[[0,1,1,1,2,2,2,3,3,3,4,5,5,6,6,6,7,7,7,8,9,9,10,10,11,11,12,12,12,13,13,13,14,14,15,15,16,16,17,17,18,18,19,19,20,20,20,21,21,21,22,23],[1,0,2,20,1,3,18,2,4,5,3,3,6,5,7,12,6,8,9,7,7,10,9,11,10,12,6,11,13,12,14,17,13,15,14,16,15,17,13,16,2,19,18,20,1,19,21,20,22,23,21,21]],\"node_feat\":[0,0,0,0,1,2,0,0,3,0,0,0,0,2,0,0,0,0,0,2,2,0,0,0],\"edge_attr\":[1,1,2,1,2,1,1,1,2,1,2,1,1,1,2,1,2,1,1,1,1,2,2,1,1,2,1,2,1,1,1,1,1,1,1,1,1,1,1,1,1,2,2,1,1,1,1,1,1,1,1,1],\"num_nodes\":24}",
          "output": "1.9317961931228638",
          "metadata_fold": "train",
          "metadata_task_type": "regression",
          "metadata_row_index": 10460,
          "metadata_num_nodes": 24,
          "metadata_num_edges": 52
        },
        {
          "input": "{\"edge_index\":[[0,1,1,2,2,2,3,3,4,4,5,5,5,6,6,7,7,7,8,8,9,9,10,10,11,11,11,12,12,12,13,14,14,15,15,16,16,16,16,17,18,19,20,20,21,21,21,22,22,23,24,24],[1,0,2,1,3,24,2,4,3,5,4,6,21,5,7,6,8,20,7,9,8,10,9,11,10,12,20,11,13,14,12,12,15,14,16,15,17,18,19,16,16,16,7,11,5,22,24,21,23,22,2,21]],\"node_feat\":[0,1,0,0,0,0,0,8,0,0,0,4,0,1,2,0,0,3,3,3,0,0,1,0,0],\"edge_attr\":[1,1,1,1,2,1,2,1,1,2,2,1,1,1,1,1,1,1,1,1,1,1,1,1,1,1,1,1,2,1,2,1,1,1,1,1,1,1,1,1,1,1,1,1,1,1,2,1,1,1,1,2],\"num_nodes\":25}",
          "output": "-1.9116958379745483",
          "metadata_fold": "train",
          "metadata_task_type": "regression",
          "metadata_row_index": 36383,
          "metadata_num_nodes": 25,
          "metadata_num_edges": 52
        },
        {
          "input": "{\"edge_index\":[[0,1,1,2,2,3,3,3,4,4,5,5,6,6,6,7,8,8,9,9,9,10,10,10,11,12,12,13,13,13,14,14,15,15,16,16,16,17,17,17,18,18,19,19,19,20,21,21,22,22,23,23,23,24],[1,0,2,1,3,2,4,9,3,5,4,6,5,7,8,6,6,9,3,8,10,9,11,12,10,10,13,12,14,23,13,15,14,16,15,17,23,16,18,22,17,19,18,20,21,19,19,22,17,21,13,16,24,23]],\"node_feat\":[0,0,1,0,0,0,0,6,0,0,4,0,2,4,0,0,2,0,0,2,0,2,0,0,1],\"edge_attr\":[1,1,1,1,1,1,2,1,2,1,1,2,2,1,1,1,1,2,1,2,1,1,1,1,1,1,1,1,1,1,1,1,1,1,1,1,1,1,2,1,2,1,1,1,1,1,1,2,1,2,1,1,2,2],\"num_nodes\":25}",
          "output": "0.254228800535202",
          "metadata_fold": "train",
          "metadata_task_type": "regression",
          "metadata_row_index": 216350,
          "metadata_num_nodes": 25,
          "metadata_num_edges": 54
        },
        {
          "input": "{\"edge_index\":[[0,1,1,2,2,2,3,3,4,4,5,5,6,6,6,7,7,7,7,8,8,9,9,10,10,10,11,12,12,12,13,13,14,14,14,15,15,16,17,17,18,18,18,19,20,20,21,21,22,22,23,23,24,24],[1,0,2,1,3,24,2,4,3,5,4,6,5,7,24,6,8,20,23,7,9,8,10,9,11,12,10,10,13,18,12,14,13,15,17,14,16,15,14,18,12,17,19,18,7,21,20,22,21,23,7,22,2,6]],\"node_feat\":[0,1,0,0,0,0,0,0,0,2,0,1,0,0,0,0,2,0,2,0,0,0,0,0,0],\"edge_attr\":[1,1,1,1,2,1,2,1,1,2,2,1,1,1,2,1,1,1,1,1,1,1,1,1,2,1,2,1,2,1,2,1,1,1,2,1,3,3,2,1,1,1,1,1,1,1,1,1,1,1,1,1,1,2],\"num_nodes\":25}",
          "output": "1.205666184425354",
          "metadata_fold": "train",
          "metadata_task_type": "regression",
          "metadata_row_index": 2113,
          "metadata_num_nodes": 25,
          "metadata_num_edges": 54
        },
        {
          "input": "{\"edge_index\":[[0,1,1,1,2,2,3,3,4,4,5,5,6,6,6,7,7,7,8,9,9,9,10,11,11,12,12,13,13,13,14,14,15,15,16,16,16,17,17,17,18,18,19,19,20,20,21,21,22,22,22,23,24,24],[1,0,2,6,1,3,2,4,3,5,4,6,1,5,7,6,8,9,7,7,10,11,9,9,12,11,13,12,14,24,13,15,14,16,15,17,24,16,18,22,17,19,18,20,19,21,20,22,17,21,23,22,13,16]],\"node_feat\":[0,0,0,0,0,0,0,0,1,2,0,0,0,0,2,1,0,0,0,0,0,0,0,6,2],\"edge_attr\":[1,1,2,1,2,1,1,2,2,1,1,2,1,2,1,1,2,1,2,1,1,1,1,1,1,1,1,1,2,1,2,1,1,1,1,1,2,1,2,1,2,1,1,2,2,1,1,2,1,2,1,1,1,2],\"num_nodes\":25}",
          "output": "2.3400135040283203",
          "metadata_fold": "train",
          "metadata_task_type": "regression",
          "metadata_row_index": 145739,
          "metadata_num_nodes": 25,
          "metadata_num_edges": 54
        },
        {
          "input": "{\"edge_index\":[[0,1,1,2,2,2,3,3,4,4,5,5,6,6,6,7,7,8,8,8,9,9,10,10,11,11,11,12,12,13,13,13,14,14,14,15,16,16,17,17,17,18,18,19,19,19,20,21,21,22,22,22,23,23,24,24,25,25],[1,0,2,1,3,25,2,4,3,5,4,6,5,7,25,6,8,7,9,24,8,10,9,11,10,12,23,11,13,12,14,22,13,15,16,14,14,17,16,18,22,17,19,18,20,21,19,19,22,13,17,21,11,24,8,23,2,6]],\"node_feat\":[0,1,0,0,0,0,0,2,0,0,0,8,0,0,0,0,2,0,5,0,0,0,2,0,0,0],\"edge_attr\":[1,1,1,1,2,1,2,1,1,2,2,1,1,1,2,1,1,1,1,1,1,1,1,1,1,1,1,1,1,1,2,1,2,1,1,1,1,2,2,1,1,1,1,1,1,2,1,2,1,1,1,1,1,1,1,1,1,2],\"num_nodes\":26}",
          "output": "-0.336241215467453",
          "metadata_fold": "train",
          "metadata_task_type": "regression",
          "metadata_row_index": 10449,
          "metadata_num_nodes": 26,
          "metadata_num_edges": 58
        },
        {
          "input": "{\"edge_index\":[[0,1,1,2,2,2,3,3,4,4,5,5,5,6,6,6,7,7,8,8,8,9,9,9,10,11,11,12,12,13,13,14,14,14,15,15,16,16,17,17,17,18,19,19,19,20,21,21,22,22,22,23,24,24,24,25],[1,0,2,1,3,7,2,4,3,5,4,6,24,5,7,8,2,6,6,9,22,8,10,11,9,9,12,11,13,12,14,13,15,21,14,16,15,17,16,18,19,17,17,20,21,19,14,19,8,23,24,22,5,22,25,24]],\"node_feat\":[0,1,0,0,0,0,0,0,0,0,1,2,2,0,0,0,0,0,1,0,1,0,0,0,2,0],\"edge_attr\":[1,1,1,1,2,1,2,1,1,2,2,1,1,1,2,1,1,2,1,1,2,1,2,1,2,1,1,1,2,2,1,1,2,1,2,1,1,2,2,1,1,1,1,1,2,1,1,2,2,1,1,1,1,1,1,1],\"num_nodes\":26}",
          "output": "1.1241371631622314",
          "metadata_fold": "train",
          "metadata_task_type": "regression",
          "metadata_row_index": 69375,
          "metadata_num_nodes": 26,
          "metadata_num_edges": 56
        },
        {
          "input": "{\"edge_index\":[[0,1,1,2,2,2,3,3,4,4,4,5,5,6,6,7,7,8,8,9,9,9,10,10,11,11,11,12,12,13,13,14,14,14,15,15,16,16,17,17,18,18,18,19,19,20,20,20,21,22,22,22,23,24,25,25],[1,0,2,1,3,11,2,4,3,5,9,4,6,5,7,6,8,7,9,4,8,10,9,11,2,10,12,11,13,12,14,13,15,25,14,16,15,17,16,18,17,19,25,18,20,19,21,22,20,20,23,24,22,22,14,18]],\"node_feat\":[0,1,0,2,0,0,0,0,0,0,0,0,0,2,0,0,0,0,0,0,2,0,0,0,1,0],\"edge_attr\":[1,1,1,1,2,1,2,1,1,2,1,2,1,1,2,2,1,1,2,1,2,1,1,2,1,2,1,1,1,1,1,1,2,1,2,1,1,2,2,1,1,1,2,1,1,1,1,1,1,1,1,2,1,2,1,2],\"num_nodes\":26}",
          "output": "2.1607439517974854",
          "metadata_fold": "train",
          "metadata_task_type": "regression",
          "metadata_row_index": 164895,
          "metadata_num_nodes": 26,
          "metadata_num_edges": 56
        },
        {
          "input": "{\"edge_index\":[[0,1,1,1,2,2,3,3,3,4,4,4,5,6,6,7,7,8,8,9,9,10,10,10,11,11,12,12,12,13,13,13,14,14,14,15,16,16,17,17,17,18,18,18,19,19,20,20,21,21,22,22,23,23,24,24,24,25,26,26],[1,0,2,26,1,3,2,4,23,3,5,6,4,4,7,6,8,7,9,8,10,9,11,16,10,12,11,13,22,12,14,17,13,15,16,14,10,14,13,18,21,17,19,22,18,20,19,21,17,20,12,18,3,24,23,25,26,24,1,24]],\"node_feat\":[0,4,0,2,0,1,0,0,5,0,0,2,0,0,0,1,2,0,0,0,0,0,5,0,4,0,1],\"edge_attr\":[1,1,1,1,1,1,1,1,1,1,2,1,2,1,1,1,1,1,1,1,1,1,2,1,2,1,1,2,1,2,1,1,1,2,1,2,1,1,1,2,1,2,1,1,1,1,1,1,1,1,1,1,1,1,1,1,1,1,1,1],\"num_nodes\":27}",
          "output": "-0.10243598371744156",
          "metadata_fold": "train",
          "metadata_task_type": "regression",
          "metadata_row_index": 175149,
          "metadata_num_nodes": 27,
          "metadata_num_edges": 60
        },
        {
          "input": "{\"edge_index\":[[0,1,1,2,2,2,3,4,4,4,5,5,6,6,7,7,7,8,8,9,9,9,10,11,11,12,12,13,13,13,14,14,15,15,16,16,16,17,17,17,18,18,18,19,20,20,21,21,22,22,23,23,23,24,25,25,26,26],[1,0,2,1,3,4,2,2,5,26,4,6,5,7,6,8,25,7,9,8,10,11,9,9,12,11,13,12,14,23,13,15,14,16,15,17,23,16,18,22,17,19,20,18,18,21,20,22,17,21,13,16,24,23,7,26,4,25]],\"node_feat\":[0,1,0,1,0,0,0,0,2,0,1,0,5,0,2,2,0,0,0,0,1,0,0,2,0,0,0],\"edge_attr\":[1,1,1,1,2,1,2,1,2,1,2,1,1,2,2,1,1,1,1,1,2,1,2,1,1,1,1,1,2,1,2,1,1,2,2,1,1,1,2,1,2,1,1,1,1,1,1,2,1,2,1,1,1,1,1,2,1,2],\"num_nodes\":27}",
          "output": "1.5218381881713867",
          "metadata_fold": "train",
          "metadata_task_type": "regression",
          "metadata_row_index": 109193,
          "metadata_num_nodes": 27,
          "metadata_num_edges": 58
        },
        {
          "input": "{\"edge_index\":[[0,1,1,1,2,2,3,3,4,4,5,5,5,6,6,7,7,7,8,8,9,9,10,10,10,11,11,12,12,12,13,13,13,14,15,15,15,16,16,17,17,18,18,19,19,20,20,20,21,21,22,22,23,23,23,24,24,25,25,26,27,27],[1,0,2,27,1,3,2,4,3,5,4,6,27,5,7,6,8,23,7,9,8,10,9,11,22,10,12,11,13,21,12,14,15,13,13,16,20,15,17,16,18,17,19,18,20,15,19,21,12,20,10,23,7,22,24,23,25,24,26,25,1,5]],\"node_feat\":[0,0,0,0,0,0,0,2,0,0,8,0,0,0,0,0,0,0,0,0,0,2,0,4,0,0,1,2],\"edge_attr\":[1,1,2,1,2,1,1,2,2,1,1,1,2,1,1,1,1,1,1,1,1,1,1,1,1,1,1,1,2,1,2,1,1,1,1,2,1,2,1,1,2,2,1,1,2,1,2,1,1,1,1,1,1,1,1,1,1,1,1,1,1,2],\"num_nodes\":28}",
          "output": "-1.595725655555725",
          "metadata_fold": "train",
          "metadata_task_type": "regression",
          "metadata_row_index": 84953,
          "metadata_num_nodes": 28,
          "metadata_num_edges": 62
        },
        {
          "input": "{\"edge_index\":[[0,1,1,2,2,2,3,3,4,4,4,5,5,6,6,6,7,8,8,8,9,9,10,10,11,11,11,12,12,12,13,13,14,14,15,15,15,16,16,17,17,17,18,19,20,20,21,21,22,22,23,23,24,24,24,25,25,26,27,27],[1,0,2,1,3,27,2,4,3,5,23,4,6,5,7,8,6,6,9,22,8,10,9,11,10,12,21,11,13,20,12,14,13,15,14,16,20,15,17,16,18,19,17,17,12,15,11,22,8,21,4,24,23,25,27,24,26,25,2,24]],\"node_feat\":[0,1,0,0,0,2,0,1,0,0,0,0,2,0,2,0,2,0,0,1,0,0,0,0,0,1,0,0],\"edge_attr\":[1,1,1,1,2,1,2,1,1,1,2,1,1,1,2,1,2,1,2,1,2,1,1,2,2,1,1,1,1,1,1,2,2,1,1,1,2,1,1,1,1,2,1,2,1,2,1,2,1,2,2,1,1,1,2,1,1,1,1,2],\"num_nodes\":28}",
          "output": "1.6154712438583374",
          "metadata_fold": "train",
          "metadata_task_type": "regression",
          "metadata_row_index": 77132,
          "metadata_num_nodes": 28,
          "metadata_num_edges": 60
        },
        {
          "input": "{\"edge_index\":[[0,1,1,1,2,2,3,3,4,4,4,5,6,6,6,7,7,8,8,9,9,9,10,10,10,11,11,12,12,13,13,14,14,15,15,16,16,17,17,18,18,19,19,19,20,20,21,21,22,22,23,23,23,24,24,24,24,25,26,27,28,28],[1,0,2,18,1,3,2,4,3,5,6,4,4,7,17,6,8,7,9,8,10,16,9,11,15,10,12,11,13,12,14,13,15,10,14,9,17,6,16,1,19,18,20,28,19,21,20,22,21,23,22,24,28,23,25,26,27,24,24,24,19,23]],\"node_feat\":[1,0,0,2,0,1,2,0,0,2,0,2,0,0,0,2,0,0,2,0,0,0,0,0,0,3,3,3,0],\"edge_attr\":[2,2,1,1,1,1,1,1,1,2,1,2,1,1,1,1,1,1,1,1,1,1,1,2,1,2,1,1,2,2,1,1,2,1,2,1,1,1,1,1,1,1,2,1,2,1,1,2,2,1,1,1,2,1,1,1,1,1,1,1,1,2],\"num_nodes\":29}",
          "output": "0.8287802934646606",
          "metadata_fold": "train",
          "metadata_task_type": "regression",
          "metadata_row_index": 196433,
          "metadata_num_nodes": 29,
          "metadata_num_edges": 62
        },
        {
          "input": "{\"edge_index\":[[0,1,1,2,2,2,3,3,4,4,5,5,5,6,6,6,7,7,7,8,8,9,9,9,10,10,10,11,11,11,12,13,13,13,14,14,15,15,15,16,17,17,18,19,19,19,20,21,21,21,22,23,23,23,24,24,24,25,26,26,26,27,28,28,29,29],[1,0,2,1,3,29,2,4,3,5,4,6,28,5,7,26,6,8,23,7,9,8,10,21,9,11,23,10,12,13,11,11,14,19,13,15,14,16,17,15,15,18,17,13,20,21,19,9,19,22,21,7,10,24,23,25,26,24,6,24,27,26,5,29,2,28]],\"node_feat\":[0,0,0,0,0,0,2,0,2,0,0,0,1,2,0,0,1,1,0,0,1,2,0,2,0,0,0,0,0,0],\"edge_attr\":[1,1,1,1,2,1,2,1,1,2,2,1,1,1,1,1,1,2,1,2,1,1,2,1,2,1,1,1,2,1,2,1,1,1,1,1,1,2,1,2,1,1,1,1,2,1,2,1,1,1,1,1,1,1,1,1,2,1,1,2,1,1,1,2,1,2],\"num_nodes\":30}",
          "output": "0.02290334552526474",
          "metadata_fold": "train",
          "metadata_task_type": "regression",
          "metadata_row_index": 175368,
          "metadata_num_nodes": 30,
          "metadata_num_edges": 66
        },
        {
          "input": "{\"edge_index\":[[0,1,1,1,2,2,3,3,4,4,4,5,5,6,6,6,7,8,8,9,9,9,10,10,10,11,12,12,13,13,13,14,14,15,15,16,16,17,17,18,18,18,19,19,19,20,20,20,21,22,22,22,23,23,24,24,25,25,25,26,27,27,28,28,29,29,30,30],[1,0,2,30,1,3,2,4,3,5,29,4,6,5,7,8,6,6,9,8,10,19,9,11,12,10,10,13,12,14,18,13,15,14,16,15,17,16,18,13,17,19,9,18,20,19,21,22,20,20,23,28,22,24,23,25,24,26,27,25,25,28,22,27,4,30,1,29]],\"node_feat\":[0,0,0,0,0,2,0,1,0,4,0,1,2,4,0,0,0,0,4,2,0,1,0,0,0,0,3,0,0,0,0],\"edge_attr\":[1,1,2,1,2,1,1,2,2,1,1,1,1,1,2,1,2,1,1,1,1,1,1,2,1,2,1,1,1,1,1,1,1,1,1,1,1,1,1,1,1,1,1,1,1,1,2,1,2,1,2,1,2,1,1,2,2,1,1,1,1,2,1,2,1,2,1,2],\"num_nodes\":31}",
          "output": "0.6179245114326477",
          "metadata_fold": "train",
          "metadata_task_type": "regression",
          "metadata_row_index": 111931,
          "metadata_num_nodes": 31,
          "metadata_num_edges": 68
        },
        {
          "input": "{\"edge_index\":[[0,1,1,1,2,2,3,3,3,4,4,5,5,6,6,6,7,7,7,8,8,9,9,10,10,11,11,11,12,12,12,13,14,15,15,16,16,17,17,17,18,18,19,19,19,20,20,21,21,22,22,22,23,24,24,25,25,26,26,26,27,27,28,28,29,29,30,30,31,31],[1,0,2,17,1,3,2,4,16,3,5,4,6,5,7,16,6,8,15,7,9,8,10,9,11,10,12,15,11,13,14,12,12,7,11,3,6,1,18,26,17,19,18,20,25,19,21,20,22,21,23,24,22,22,25,19,24,17,27,31,26,28,27,29,28,30,29,31,26,30]],\"node_feat\":[1,0,0,2,0,2,0,0,0,0,0,0,12,1,7,0,2,2,0,0,0,0,0,3,0,0,0,0,0,0,0,0],\"edge_attr\":[2,2,1,1,1,1,1,1,1,1,2,2,1,1,1,2,1,2,1,2,1,1,2,2,1,1,1,2,1,2,1,2,1,1,2,1,2,1,1,1,1,1,1,2,1,2,1,1,2,2,1,1,1,1,2,1,2,1,1,1,1,1,1,1,1,1,1,1,1,1],\"num_nodes\":32}",
          "output": "2.1957812309265137",
          "metadata_fold": "train",
          "metadata_task_type": "regression",
          "metadata_row_index": 75881,
          "metadata_num_nodes": 32,
          "metadata_num_edges": 70
        },
        {
          "input": "{\"edge_index\":[[0,1,1,2,2,3,3,3,4,4,5,5,6,6,7,7,8,8,8,9],[1,0,2,1,3,2,4,8,3,5,4,6,5,7,6,8,3,7,9,8]],\"node_feat\":[1,2,0,0,0,0,0,2,0,6],\"edge_attr\":[1,1,2,2,1,1,2,1,2,1,1,2,2,1,1,2,1,2,1,1],\"num_nodes\":10}",
          "output": "-0.022982697933912277",
          "metadata_fold": "val",
          "metadata_task_type": "regression",
          "metadata_row_index": 8185,
          "metadata_num_nodes": 10,
          "metadata_num_edges": 20
        },
        {
          "input": "{\"edge_index\":[[0,1,1,1,2,2,3,3,4,4,4,5,6,6,6,7,7,8,8,9,9,10,10,11,11,11,12,12,13,13,14,14,15,15,16,16],[1,0,2,6,1,3,2,4,3,5,6,4,1,4,7,6,8,7,9,8,10,9,11,10,12,16,11,13,12,14,13,15,14,16,11,15]],\"node_feat\":[0,0,2,1,0,0,0,0,2,0,0,0,0,0,0,2,0],\"edge_attr\":[1,1,2,1,2,1,1,1,1,1,2,1,1,2,1,1,1,1,1,1,1,1,1,1,2,1,2,1,1,2,2,1,1,2,1,2],\"num_nodes\":17}",
          "output": "0.9542816877365112",
          "metadata_fold": "val",
          "metadata_task_type": "regression",
          "metadata_row_index": 19319,
          "metadata_num_nodes": 17,
          "metadata_num_edges": 36
        },
        {
          "input": "{\"edge_index\":[[0,1,1,1,2,2,2,3,3,3,4,5,6,6,7,7,8,8,9,9,9,10,10,11,11,11,12,12,13,13,14,14,14,15,16,16,17,17,17,18],[1,0,2,9,1,3,6,2,4,5,3,3,2,7,6,8,7,9,1,8,10,9,11,10,12,17,11,13,12,14,13,15,16,14,14,17,11,16,18,17]],\"node_feat\":[1,0,0,12,1,7,0,0,0,2,0,0,0,0,0,3,0,0,6],\"edge_attr\":[2,2,1,1,1,1,2,1,2,1,2,1,2,1,1,2,2,1,1,1,1,1,1,1,2,1,2,1,1,2,2,1,1,1,1,2,1,2,1,1],\"num_nodes\":19}",
          "output": "1.3505492210388184",
          "metadata_fold": "val",
          "metadata_task_type": "regression",
          "metadata_row_index": 819,
          "metadata_num_nodes": 19,
          "metadata_num_edges": 40
        },
        {
          "input": "{\"edge_index\":[[0,1,1,2,2,3,3,3,4,4,5,5,5,6,6,6,7,8,8,9,9,9,10,10,10,11,11,12,12,13,13,14,14,15,15,15,16,16,17,17,17,18,19,19,20,20],[1,0,2,1,3,2,4,20,3,5,4,6,19,5,7,8,6,6,9,8,10,17,9,11,15,10,12,11,13,12,14,13,15,10,14,16,15,17,9,16,18,17,5,20,3,19]],\"node_feat\":[0,1,0,0,2,0,0,1,2,4,0,0,0,0,0,0,0,4,1,0,5],\"edge_attr\":[1,1,1,1,1,1,2,1,2,1,1,1,2,1,2,1,2,1,1,1,1,1,1,2,1,2,1,1,2,2,1,1,2,1,2,1,1,1,1,1,1,1,2,1,1,1],\"num_nodes\":21}",
          "output": "-0.41205838322639465",
          "metadata_fold": "val",
          "metadata_task_type": "regression",
          "metadata_row_index": 23954,
          "metadata_num_nodes": 21,
          "metadata_num_edges": 46
        },
        {
          "input": "{\"edge_index\":[[0,1,1,1,2,3,3,3,4,4,5,5,6,6,6,7,7,7,8,9,9,9,10,10,11,11,12,12,13,13,13,14,15,15,16,16,16,17,17,18,18,19,19,20,20,21,21,21],[1,0,2,3,1,1,4,21,3,5,4,6,5,7,16,6,8,9,7,7,10,15,9,11,10,12,11,13,12,14,15,13,9,13,6,17,21,16,18,17,19,18,20,19,21,3,16,20]],\"node_feat\":[2,0,1,4,0,0,2,0,1,0,0,0,0,0,6,0,0,0,0,0,0,0],\"edge_attr\":[1,1,2,1,2,1,1,1,1,1,1,1,1,1,1,1,2,1,2,1,2,1,2,1,1,2,2,1,1,1,2,1,1,2,1,2,1,2,1,1,2,2,1,1,2,1,1,2],\"num_nodes\":22}",
          "output": "1.1024788618087769",
          "metadata_fold": "val",
          "metadata_task_type": "regression",
          "metadata_row_index": 15879,
          "metadata_num_nodes": 22,
          "metadata_num_edges": 48
        },
        {
          "input": "{\"edge_index\":[[0,1,1,1,2,2,3,3,3,4,4,5,5,6,6,7,7,7,8,8,8,9,9,10,10,11,11,12,12,13,13,14,14,14,15,15,16,16,17,17,18,18,18,19,19,19,20,20,21,21,22,22],[1,0,2,14,1,3,2,4,13,3,5,4,6,5,7,6,8,13,7,9,12,8,10,9,11,10,12,8,11,3,7,1,15,19,14,16,15,17,16,18,17,19,22,14,18,20,19,21,20,22,18,21]],\"node_feat\":[1,0,2,0,0,0,0,0,2,0,2,2,2,0,0,0,0,0,0,0,0,0,2],\"edge_attr\":[2,2,1,1,1,1,1,2,1,2,1,1,2,2,1,1,1,2,1,1,1,1,2,2,1,1,2,1,2,1,2,1,2,1,2,1,1,2,2,1,1,2,1,1,2,1,1,2,2,1,1,1],\"num_nodes\":23}",
          "output": "1.1680876016616821",
          "metadata_fold": "val",
          "metadata_task_type": "regression",
          "metadata_row_index": 22046,
          "metadata_num_nodes": 23,
          "metadata_num_edges": 52
        },
        {
          "input": "{\"edge_index\":[[0,1,1,1,2,2,3,3,3,3,4,5,5,6,6,7,7,8,8,9,9,10,10,11,11,12,12,12,13,13,14,14,15,15,15,16,16,16,17,17,18,18,19,19,20,20,21,21,22,22,23,23],[1,0,2,10,1,3,2,4,5,9,3,3,6,5,7,6,8,7,9,3,8,1,11,10,12,11,13,23,12,14,13,15,14,16,22,15,17,21,16,18,17,19,18,20,19,21,16,20,15,23,12,22]],\"node_feat\":[1,0,0,0,1,0,0,0,0,0,2,0,0,0,0,0,0,0,0,0,2,0,0,0],\"edge_attr\":[2,2,1,1,1,1,1,1,1,1,1,1,1,1,1,1,1,1,1,1,1,1,1,1,1,1,2,1,2,1,1,2,2,1,1,1,2,1,2,1,1,2,2,1,1,2,1,2,1,2,1,2],\"num_nodes\":24}",
          "output": "1.9039634466171265",
          "metadata_fold": "val",
          "metadata_task_type": "regression",
          "metadata_row_index": 2339,
          "metadata_num_nodes": 24,
          "metadata_num_edges": 52
        },
        {
          "input": "{\"edge_index\":[[0,1,1,1,2,2,3,3,4,4,4,5,5,6,6,7,7,7,8,9,9,10,10,11,11,12,12,12,13,13,14,14,14,15,16,16,16,17,18,18,18,19,20,20,20,21,22,22,22,23,24,24],[1,0,2,24,1,3,2,4,3,5,22,4,6,5,7,6,8,9,7,7,10,9,11,10,12,11,13,20,12,14,13,15,16,14,14,17,18,16,16,19,20,18,12,18,21,20,4,23,24,22,1,22]],\"node_feat\":[0,0,0,0,0,1,0,0,1,2,2,0,0,0,0,9,0,1,0,9,0,1,0,0,0],\"edge_attr\":[1,1,2,1,2,1,1,2,2,1,1,1,1,1,1,1,2,1,2,1,1,1,2,2,1,1,2,1,2,1,1,1,2,1,2,1,1,1,1,1,2,1,1,2,1,1,1,1,2,1,1,2],\"num_nodes\":25}",
          "output": "1.7656179666519165",
          "metadata_fold": "val",
          "metadata_task_type": "regression",
          "metadata_row_index": 21895,
          "metadata_num_nodes": 25,
          "metadata_num_edges": 52
        },
        {
          "input": "{\"edge_index\":[[0,1,1,1,1,2,3,3,4,4,5,5,5,6,6,7,7,8,8,9,9,10,10,11,11,12,12,12,13,13,14,14,15,15,15,16,16,16,17,17,18,18,18,19,19,20,20,21,21,22,22,22,23,23,24,24,25,25],[1,0,2,3,11,1,1,4,3,5,4,6,10,5,7,6,8,7,9,8,10,5,9,1,12,11,13,25,12,14,13,15,14,16,24,15,17,23,16,18,17,19,22,18,20,19,21,20,22,18,21,23,16,22,15,25,12,24]],\"node_feat\":[1,5,1,0,0,0,0,0,0,0,0,2,0,0,0,0,0,0,2,0,0,5,0,2,0,0],\"edge_attr\":[2,2,2,1,1,2,1,2,2,1,1,2,1,2,1,1,2,2,1,1,2,1,2,1,1,1,2,1,2,1,1,2,2,1,1,1,2,1,2,1,1,1,1,1,2,2,1,1,1,1,1,2,1,2,1,2,1,2],\"num_nodes\":26}",
          "output": "2.345183849334717",
          "metadata_fold": "val",
          "metadata_task_type": "regression",
          "metadata_row_index": 15411,
          "metadata_num_nodes": 26,
          "metadata_num_edges": 58
        },
        {
          "input": "{\"edge_index\":[[0,1,1,2,2,3,3,3,4,5,5,5,6,6,6,7,7,8,8,8,9,10,10,11,11,12,12,12,13,13,14,14,15,15,16,16,16,17,17,17,18,18,19,19,20,20,21,21,22,22,22,23,23,23,24,24,25,25,26,26,27,27,28,28],[1,0,2,1,3,2,4,5,3,3,6,23,5,7,21,6,8,7,9,10,8,8,11,10,12,11,13,17,12,14,13,15,14,16,15,17,20,12,16,18,17,19,18,20,16,19,6,22,21,23,28,5,22,24,23,25,24,26,25,27,26,28,22,27]],\"node_feat\":[0,0,1,0,1,0,0,2,0,1,0,5,0,2,0,2,0,0,0,0,5,5,0,0,0,0,0,0,0],\"edge_attr\":[1,1,1,1,1,1,2,1,2,1,2,1,2,1,1,1,1,1,2,1,2,1,1,1,1,1,2,1,2,1,1,2,2,1,1,2,1,1,2,1,1,2,2,1,1,1,1,1,1,2,1,1,2,1,1,1,1,1,1,1,1,1,1,1],\"num_nodes\":29}",
          "output": "-0.9535728693008423",
          "metadata_fold": "val",
          "metadata_task_type": "regression",
          "metadata_row_index": 2254,
          "metadata_num_nodes": 29,
          "metadata_num_edges": 64
        },
        {
          "input": "{\"edge_index\":[[0,1,1,1,2,3,3,3,4,5,5,5,6,6,7,7,8,8,8,9,10,10],[1,0,2,3,1,1,4,5,3,3,6,10,5,7,6,8,7,9,10,8,5,8]],\"node_feat\":[0,4,10,0,1,2,0,0,4,1,0],\"edge_attr\":[1,1,1,1,1,1,2,1,2,1,1,1,1,1,1,1,1,1,1,1,1,1],\"num_nodes\":11}",
          "output": "-3.8562958240509033",
          "metadata_fold": "test",
          "metadata_task_type": "regression",
          "metadata_row_index": 2542,
          "metadata_num_nodes": 11,
          "metadata_num_edges": 22
        },
        {
          "input": "{\"edge_index\":[[0,1,1,1,2,3,3,4,4,4,5,6,6,6,7,8,8,9,9,9,10,10,11,11,12,12,12,13,14,14,14,15,16,16],[1,0,2,3,1,1,4,3,5,6,4,4,7,8,6,6,9,8,10,16,9,11,10,12,11,13,14,12,12,15,16,14,9,14]],\"node_feat\":[0,0,1,2,4,0,0,1,2,0,0,0,0,3,0,6,0],\"edge_attr\":[1,1,2,1,2,1,1,1,1,1,1,1,2,1,2,1,1,1,2,1,2,1,1,2,2,1,1,1,1,1,2,1,1,2],\"num_nodes\":17}",
          "output": "0.8461156487464905",
          "metadata_fold": "test",
          "metadata_task_type": "regression",
          "metadata_row_index": 1450,
          "metadata_num_nodes": 17,
          "metadata_num_edges": 34
        },
        {
          "input": "{\"edge_index\":[[0,1,1,2,2,2,3,3,4,4,5,5,5,6,6,7,7,8,8,9,9,9,10,11,11,11,12,12,13,13,14,14,15,15,16,16,17,17,18,18],[1,0,2,1,3,18,2,4,3,5,4,6,17,5,7,6,8,7,9,8,10,11,9,9,12,16,11,13,12,14,13,15,14,16,11,15,5,18,2,17]],\"node_feat\":[0,1,0,0,0,0,0,0,2,0,1,0,0,0,2,0,0,0,0],\"edge_attr\":[1,1,1,1,2,1,2,1,1,2,2,1,1,1,1,1,1,1,1,1,2,1,2,1,2,1,2,1,1,2,2,1,1,2,1,2,1,2,1,2],\"num_nodes\":19}",
          "output": "1.6475038528442383",
          "metadata_fold": "test",
          "metadata_task_type": "regression",
          "metadata_row_index": 2211,
          "metadata_num_nodes": 19,
          "metadata_num_edges": 40
        },
        {
          "input": "{\"edge_index\":[[0,1,1,2,2,3,3,3,4,4,5,5,6,6,7,7,7,8,8,9,9,10,10,10,11,11,12,12,13,13,13,14,15,15,16,16,16,17,17,18,18,18,19,20],[1,0,2,1,3,2,4,7,3,5,4,6,5,7,3,6,8,7,9,8,10,9,11,16,10,12,11,13,12,14,15,13,13,16,10,15,17,16,18,17,19,20,18,18]],\"node_feat\":[0,0,0,2,2,0,2,0,0,1,0,0,0,0,0,2,0,0,4,0,10],\"edge_attr\":[1,1,1,1,1,1,1,1,1,2,2,1,1,2,1,2,1,1,1,1,1,1,2,1,2,1,1,2,2,1,1,1,1,2,1,2,1,1,1,1,1,1,1,1],\"num_nodes\":21}",
          "output": "-1.3404091596603394",
          "metadata_fold": "test",
          "metadata_task_type": "regression",
          "metadata_row_index": 687,
          "metadata_num_nodes": 21,
          "metadata_num_edges": 44
        },
        {
          "input": "{\"edge_index\":[[0,1,1,2,2,2,3,3,4,4,5,5,5,6,7,7,8,8,8,9,9,9,10,11,11,12,12,13,13,13,14,14,15,15,15,16,16,16,17,17,18,18,19,19,20,20,21,21],[1,0,2,1,3,8,2,4,3,5,4,6,7,5,5,8,2,7,9,8,10,11,9,9,12,11,13,12,14,21,13,15,14,16,19,15,17,18,16,18,16,17,15,20,19,21,13,20]],\"node_feat\":[0,1,0,0,0,0,0,0,0,4,0,2,0,4,0,2,0,0,0,0,0,1],\"edge_attr\":[1,1,1,1,2,1,2,1,1,2,2,1,1,1,1,2,1,2,1,1,1,1,1,1,1,1,1,1,1,1,1,1,1,1,1,1,1,1,1,1,1,1,1,1,1,1,1,1],\"num_nodes\":22}",
          "output": "0.2700461745262146",
          "metadata_fold": "test",
          "metadata_task_type": "regression",
          "metadata_row_index": 606,
          "metadata_num_nodes": 22,
          "metadata_num_edges": 48
        },
        {
          "input": "{\"edge_index\":[[0,1,1,1,2,2,3,3,4,4,4,5,5,6,6,6,7,8,8,8,9,10,10,11,11,12,12,12,13,13,14,14,15,15,15,16,17,17,17,18,19,19,20,20,20,21,22,22],[1,0,2,22,1,3,2,4,3,5,20,4,6,5,7,8,6,6,9,10,8,8,11,10,12,11,13,19,12,14,13,15,14,16,17,15,15,18,19,17,12,17,4,21,22,20,1,20]],\"node_feat\":[0,0,0,0,0,2,0,1,0,1,2,0,0,0,0,0,3,0,0,0,0,6,2],\"edge_attr\":[1,1,2,1,2,1,1,2,2,1,1,1,1,1,2,1,2,1,2,1,2,1,1,1,1,1,2,1,2,1,1,2,2,1,1,1,1,1,2,1,1,2,1,1,2,1,1,2],\"num_nodes\":23}",
          "output": "1.4308502674102783",
          "metadata_fold": "test",
          "metadata_task_type": "regression",
          "metadata_row_index": 4393,
          "metadata_num_nodes": 23,
          "metadata_num_edges": 48
        },
        {
          "input": "{\"edge_index\":[[0,1,1,1,2,2,2,3,3,4,4,5,5,6,6,7,7,7,8,8,9,9,9,10,10,11,11,12,12,12,13,14,14,14,15,15,16,16,17,17,18,18,18,19,19,19,19,20,21,22,23,23],[1,0,2,9,1,3,7,2,4,3,5,4,6,5,7,2,6,8,7,9,1,8,10,9,11,10,12,11,13,14,12,12,15,23,14,16,15,17,16,18,17,19,23,18,20,21,22,19,19,19,14,18]],\"node_feat\":[0,2,0,0,0,0,0,0,2,0,0,2,0,1,0,0,0,0,0,0,3,3,3,0],\"edge_attr\":[1,1,1,1,1,2,1,2,1,1,2,2,1,1,2,1,2,1,1,2,1,2,1,1,1,1,1,1,2,1,2,1,2,1,2,1,1,2,2,1,1,1,2,1,1,1,1,1,1,1,1,2],\"num_nodes\":24}",
          "output": "2.2132930755615234",
          "metadata_fold": "test",
          "metadata_task_type": "regression",
          "metadata_row_index": 1990,
          "metadata_num_nodes": 24,
          "metadata_num_edges": 52
        },
        {
          "input": "{\"edge_index\":[[0,1,1,1,2,2,3,3,4,4,4,5,5,6,6,6,7,8,8,9,9,10,10,11,11,11,12,12,13,13,13,14,14,14,15,15,16,16,17,17,17,18,19,19,20,20,21,21,22,22,23,23,24,24],[1,0,2,24,1,3,2,4,3,5,23,4,6,5,7,8,6,6,9,8,10,9,11,10,12,22,11,13,12,14,21,13,15,20,14,16,15,17,16,18,19,17,17,20,14,19,13,22,11,21,4,24,1,23]],\"node_feat\":[0,0,0,0,0,2,0,1,2,0,0,0,2,0,0,0,0,0,6,0,0,0,5,0,0],\"edge_attr\":[1,1,2,1,2,1,1,2,2,1,1,1,1,1,2,1,2,1,1,1,1,1,1,1,2,1,2,1,1,1,2,1,2,1,2,1,1,2,2,1,1,1,1,2,1,2,2,1,1,1,1,2,1,2],\"num_nodes\":25}",
          "output": "3.391331434249878",
          "metadata_fold": "test",
          "metadata_task_type": "regression",
          "metadata_row_index": 4966,
          "metadata_num_nodes": 25,
          "metadata_num_edges": 54
        },
        {
          "input": "{\"edge_index\":[[0,1,1,2,2,2,3,3,4,4,4,5,6,6,7,7,7,8,8,9,9,9,10,11,11,11,12,13,13,14,14,14,15,16,16,16,17,17,18,18,19,19,19,20,20,20,21,21,22,22,23,23,24,24,25,25,26,26],[1,0,2,1,3,7,2,4,3,5,6,4,4,7,2,6,8,7,9,8,10,11,9,9,12,13,11,11,14,13,15,16,14,14,17,26,16,18,17,19,18,20,26,19,21,25,20,22,21,23,22,24,23,25,20,24,16,19]],\"node_feat\":[0,0,0,2,2,0,0,0,2,0,1,0,1,2,4,0,0,2,0,0,0,0,0,0,0,0,1],\"edge_attr\":[1,1,1,1,2,1,2,1,1,1,1,1,1,2,1,2,1,1,1,1,2,1,2,1,2,1,2,1,1,1,1,1,1,1,2,1,2,1,1,2,2,1,1,1,2,1,2,1,1,2,2,1,1,2,1,2,1,1],\"num_nodes\":27}",
          "output": "0.09377928078174591",
          "metadata_fold": "test",
          "metadata_task_type": "regression",
          "metadata_row_index": 2795,
          "metadata_num_nodes": 27,
          "metadata_num_edges": 58
        },
        {
          "input": "{\"edge_index\":[[0,1,1,2,2,2,3,3,4,4,4,5,5,5,5,6,7,8,8,8,9,9,10,10,11,11,12,12,13,13,14,14,14,15,15,15,16,16,17,17,17,18,18,18,19,19,20,20,21,21,21,22,23,23,24,24,25,25,26,26,27,27,28,28],[1,0,2,1,3,28,2,4,3,5,27,4,6,7,8,5,5,5,9,14,8,10,9,11,10,12,11,13,12,14,8,13,15,14,16,26,15,17,16,18,25,17,19,24,18,20,19,21,20,22,23,21,21,24,18,23,17,26,15,25,4,28,2,27]],\"node_feat\":[0,0,2,0,0,5,1,1,2,0,0,0,0,0,4,0,0,0,0,0,0,0,3,0,0,2,1,0,2],\"edge_attr\":[1,1,1,1,1,1,1,2,2,1,1,1,2,2,1,2,2,1,1,1,1,1,1,1,1,1,1,1,1,1,1,1,1,1,2,1,2,1,1,1,2,1,2,1,2,1,1,2,2,1,1,1,1,2,1,2,2,1,1,1,1,2,1,2],\"num_nodes\":29}",
          "output": "-2.1670033931732178",
          "metadata_fold": "test",
          "metadata_task_type": "regression",
          "metadata_row_index": 45,
          "metadata_num_nodes": 29,
          "metadata_num_edges": 64
        }
      ]
    }
  ],
  "precomputed_analysis": {
    "rwpe_16": {
      "test_mae_mean": 0.10106794706980388,
      "test_mae_std": 0.0020175987747092262,
      "val_mae_mean": 0.13078030490875245,
      "val_mae_std": 0.0034510492834680744,
      "best_epoch_mean": 241.66666666666666,
      "test_maes": [
        0.10391995143890381,
        0.09956704139709473,
        0.09971684837341309
      ],
      "val_maes": [
        0.13520230102539063,
        0.12678071117401124,
        0.13035790252685547
      ],
      "best_epochs": [
        237,
        243,
        245
      ],
      "num_params": 262593
    },
    "concat_32": {
      "test_mae_mean": 0.10615527311960855,
      "test_mae_std": 0.001749902072568096,
      "val_mae_mean": 0.13303493213653564,
      "val_mae_std": 0.0019969795352317394,
      "best_epoch_mean": 244.66666666666666,
      "test_maes": [
        0.10369034385681153,
        0.10719713687896729,
        0.10757833862304687
      ],
      "val_maes": [
        0.1308380012512207,
        0.13259651374816894,
        0.13567028141021728
      ],
      "best_epochs": [
        234,
        250,
        250
      ],
      "num_params": 264641,
      "vs_rwpe16_ttest_t": -1.913027788415407,
      "vs_rwpe16_ttest_p": 0.19587137945396624,
      "vs_rwpe16_improvement": -0.005087326049804677,
      "win_rate_vs_rwpe16": {
        "wins": 473,
        "ties": 0,
        "losses": 527,
        "win_pct": 47.3
      }
    },
    "concat_24": {
      "test_mae_mean": 0.10724140803019205,
      "test_mae_std": 0.002760893166058637,
      "val_mae_mean": 0.1359885301589966,
      "val_mae_std": 0.0021730875619040187,
      "best_epoch_mean": 189.66666666666666,
      "test_maes": [
        0.11103155899047852,
        0.10453401279449463,
        0.10615865230560302
      ],
      "val_maes": [
        0.13337547779083253,
        0.13589418792724609,
        0.13869592475891113
      ],
      "best_epochs": [
        209,
        212,
        148
      ],
      "num_params": 263617,
      "vs_rwpe16_ttest_t": -9.745388855743535,
      "vs_rwpe16_ttest_p": 0.01036591697614083,
      "vs_rwpe16_improvement": -0.006173460960388177,
      "win_rate_vs_rwpe16": {
        "wins": 475,
        "ties": 0,
        "losses": 525,
        "win_pct": 47.5
      }
    },
    "concat_16": {
      "test_mae_mean": 0.10693389097849527,
      "test_mae_std": 0.0018230894420991333,
      "val_mae_mean": 0.14077320925394696,
      "val_mae_std": 0.0020869671587575144,
      "best_epoch_mean": 145.66666666666666,
      "test_maes": [
        0.10886368179321289,
        0.10744967555999756,
        0.10448831558227539
      ],
      "val_maes": [
        0.14352195739746093,
        0.13846800994873046,
        0.14032966041564943
      ],
      "best_epochs": [
        137,
        150,
        150
      ],
      "num_params": 262593,
      "vs_rwpe16_ttest_t": -5.810335564146846,
      "vs_rwpe16_ttest_p": 0.02836653650750058,
      "vs_rwpe16_improvement": -0.005865943908691398,
      "win_rate_vs_rwpe16": {
        "wins": 449,
        "ties": 0,
        "losses": 551,
        "win_pct": 44.9
      }
    },
    "nrwpe_tanh_16": {
      "test_mae_mean": 0.12013374710083008,
      "test_mae_std": 0.0008398714789423611,
      "val_mae_mean": 0.1541769059499105,
      "val_mae_std": 0.0036642968884075806,
      "best_epoch_mean": 143.0,
      "test_maes": [
        0.11897764778137207,
        0.12094770336151123,
        0.12047589015960693
      ],
      "val_maes": [
        0.15135373306274413,
        0.15182513236999512,
        0.15935185241699218
      ],
      "best_epochs": [
        137,
        149,
        143
      ],
      "num_params": 262593,
      "vs_rwpe16_ttest_t": -9.475715157524448,
      "vs_rwpe16_ttest_p": 0.010954531417092569,
      "vs_rwpe16_improvement": -0.019065800031026203,
      "win_rate_vs_rwpe16": {
        "wins": 463,
        "ties": 0,
        "losses": 537,
        "win_pct": 46.300000000000004
      }
    },
    "no_pe": {
      "test_mae_mean": 0.1930136604309082,
      "test_mae_std": 0.0036751060485839815,
      "val_mae_mean": 0.20054782676696778,
      "val_mae_std": 0.002608928680419925,
      "best_epoch_mean": 141.0,
      "test_maes": [
        0.19668876647949218,
        0.18933855438232422
      ],
      "val_maes": [
        0.2031567554473877,
        0.19793889808654785
      ],
      "best_epochs": [
        143,
        139
      ],
      "num_params": 243841,
      "vs_rwpe16_ttest_t": -60.901545674869155,
      "vs_rwpe16_ttest_p": 0.010452322031846406,
      "vs_rwpe16_improvement": -0.09194571336110433,
      "win_rate_vs_rwpe16": {
        "wins": 406,
        "ties": 0,
        "losses": 594,
        "win_pct": 40.6
      }
    },
    "mild_16": {
      "test_mae_mean": 0.18192610549926758,
      "test_mae_std": 0.001590913772582997,
      "val_mae_mean": 0.1935208683013916,
      "val_mae_std": 0.003088132858276374,
      "best_epoch_mean": 147.5,
      "test_maes": [
        0.18351701927185057,
        0.18033519172668458
      ],
      "val_maes": [
        0.19660900115966798,
        0.19043273544311523
      ],
      "best_epochs": [
        145,
        150
      ],
      "num_params": 262593,
      "vs_rwpe16_ttest_t": -136.9375928871139,
      "vs_rwpe16_ttest_p": 0.0046488947466673996,
      "vs_rwpe16_improvement": -0.0808581584294637,
      "win_rate_vs_rwpe16": {
        "wins": 399,
        "ties": 0,
        "losses": 601,
        "win_pct": 39.900000000000006
      }
    }
  },
  "precomputed_pe_configs": {
    "rwpe_16": {
      "rwpe_k": 16,
      "nrwpe_k": 0,
      "mild_k": 0,
      "pe_dim": 16
    },
    "nrwpe_tanh_16": {
      "rwpe_k": 0,
      "nrwpe_k": 16,
      "mild_k": 0,
      "pe_dim": 16
    },
    "concat_16": {
      "rwpe_k": 8,
      "nrwpe_k": 8,
      "mild_k": 0,
      "pe_dim": 16
    },
    "concat_24": {
      "rwpe_k": 16,
      "nrwpe_k": 8,
      "mild_k": 0,
      "pe_dim": 24
    },
    "concat_32": {
      "rwpe_k": 16,
      "nrwpe_k": 16,
      "mild_k": 0,
      "pe_dim": 32
    },
    "mild_16": {
      "rwpe_k": 0,
      "nrwpe_k": 0,
      "mild_k": 16,
      "pe_dim": 16
    },
    "rwpe_24": {
      "rwpe_k": 24,
      "nrwpe_k": 0,
      "mild_k": 0,
      "pe_dim": 24
    },
    "rwpe_32": {
      "rwpe_k": 32,
      "nrwpe_k": 0,
      "mild_k": 0,
      "pe_dim": 32
    },
    "no_pe": {
      "rwpe_k": 0,
      "nrwpe_k": 0,
      "mild_k": 0,
      "pe_dim": 16
    }
  }
}